easy_bloom_filter/__init__.py
easy_bloom_filter/bloom_filter.py
easy_bloom_filter-0.1.0.dist-info/LICENSE
easy_bloom_filter-0.1.0.dist-info/METADATA
easy_bloom_filter-0.1.0.dist-info/WHEEL
easy_bloom_filter-0.1.0.dist-info/top_level.txt
easy_bloom_filter-0.1.0.dist-info/RECORD
