Metadata-Version: 2.1
Name: easy-bloom-filter
Version: 0.1.0
Summary: python implementation of bloom filter
Home-page: https://github.com/hvuhsg/py-bloom-filter
Author: yehoyada.sht
Author-email: yehoyada.sht@gmail.com
Maintainer: yehoyada.sht
Maintainer-email: yehoyada.sht@gmail.com
License: MIT
Keywords: bloom,filter
Platform: UNKNOWN
Classifier: Development Status :: 5 - Production/Stable
Classifier: Intended Audience :: Developers
Classifier: Topic :: Software Development
Classifier: License :: OSI Approved :: MIT License
Classifier: Programming Language :: Python :: 3
Classifier: Programming Language :: Python :: 3.5
Classifier: Programming Language :: Python :: 3.6
Classifier: Programming Language :: Python :: 3.7
Classifier: Programming Language :: Python :: 3.8
Classifier: Programming Language :: Python :: 3.9
Classifier: Programming Language :: Python :: 3.10
License-File: LICENSE
